[
    {
        "nombre": "Juega + Pega +",
        "numeros": [
            "10",
            "22",
            "15",
            "26",
            "12"
        ],
        "fecha": "07/05/2026"
    },
    {
        "nombre": "Gana Más",
        "numeros": [
            "74",
            "65",
            "02"
        ],
        "fecha": "07/05/2026"
    },
    {
        "nombre": "Lotería Nacional",
        "numeros": [
            "51",
            "74",
            "58"
        ],
        "fecha": "07/05/2026"
    },
    {
        "nombre": "Pega 3 Más",
        "numeros": [
            "21",
            "39",
            "41"
        ],
        "fecha": "07/05/2026"
    },
    {
        "nombre": "Quiniela Leidsa",
        "numeros": [
            "35",
            "09",
            "71"
        ],
        "fecha": "07/05/2026"
    },
    {
        "nombre": "Loto Pool",
        "numeros": [
            "05",
            "23",
            "25",
            "29",
            "31"
        ],
        "fecha": "07/05/2026"
    },
    {
        "nombre": "Super Kino TV",
        "numeros": [
            "04",
            "07",
            "10",
            "15",
            "16",
            "17",
            "18",
            "20",
            "25",
            "32",
            "38",
            "40",
            "45",
            "51",
            "63",
            "64",
            "65",
            "69",
            "70",
            "73"
        ],
        "fecha": "07/05/2026"
    },
    {
        "nombre": "Loto - Super Loto Más",
        "numeros": [
            "02",
            "03",
            "08",
            "10",
            "13",
            "19",
            "04",
            "10"
        ],
        "fecha": "07/05/2026"
    },
    {
        "nombre": "Loto Pool",
        "numeros": [
            "84",
            "69",
            "04",
            "20"
        ],
        "fecha": "07/05/2026"
    },
    {
        "nombre": "Quiniela Real",
        "numeros": [
            "59",
            "23",
            "56"
        ],
        "fecha": "07/05/2026"
    },
    {
        "nombre": "Loto Real",
        "numeros": [
            "05",
            "18",
            "20",
            "28",
            "31",
            "38"
        ],
        "fecha": "07/05/2026"
    },
    {
        "nombre": "Loto Pool Noche",
        "numeros": [
            "80",
            "47",
            "13",
            "57"
        ],
        "fecha": "07/05/2026"
    },
    {
        "nombre": "Quiniela Loteka",
        "numeros": [
            "18",
            "95",
            "98"
        ],
        "fecha": "07/05/2026"
    },
    {
        "nombre": "Mega Chances",
        "numeros": [
            "71",
            "04",
            "78",
            "83",
            "34"
        ],
        "fecha": "07/05/2026"
    },
    {
        "nombre": "MegaLotto",
        "numeros": [
            "04",
            "15",
            "21",
            "26",
            "29",
            "38",
            "10",
            "03"
        ],
        "fecha": "07/05/2026"
    },
    {
        "nombre": "Florida Día",
        "numeros": [
            "72",
            "25",
            "60"
        ],
        "fecha": "07/05/2026"
    },
    {
        "nombre": "New York Tarde",
        "numeros": [
            "19",
            "59",
            "54"
        ],
        "fecha": "07/05/2026"
    },
    {
        "nombre": "Florida Noche",
        "numeros": [
            "17",
            "93",
            "36"
        ],
        "fecha": "07/05/2026"
    },
    {
        "nombre": "New York Noche",
        "numeros": [
            "02",
            "26",
            "53"
        ],
        "fecha": "07/05/2026"
    },
    {
        "nombre": "Mega Millions",
        "numeros": [
            "12",
            "22",
            "50",
            "51",
            "55",
            "10"
        ],
        "fecha": "07/05/2026"
    },
    {
        "nombre": "PowerBall",
        "numeros": [
            "18",
            "27",
            "51",
            "65",
            "68",
            "05",
            "3X"
        ],
        "fecha": "07/05/2026"
    },
    {
        "nombre": "Cash 4 Life",
        "numeros": [
            "25",
            "52",
            "20",
            "55",
            "30",
            "04"
        ],
        "fecha": "07/05/2026"
    },
    {
        "nombre": "La Primera Día",
        "numeros": [
            "47",
            "32",
            "09"
        ],
        "fecha": "07/05/2026"
    },
    {
        "nombre": "Primera Noche",
        "numeros": [
            "85",
            "64",
            "64"
        ],
        "fecha": "07/05/2026"
    },
    {
        "nombre": "Loto 5",
        "numeros": [
            "11",
            "24",
            "31",
            "33",
            "23",
            "08"
        ],
        "fecha": "07/05/2026"
    },
    {
        "nombre": "La Suerte 12:30",
        "numeros": [
            "91",
            "33",
            "53"
        ],
        "fecha": "07/05/2026"
    },
    {
        "nombre": "La Suerte 18:00",
        "numeros": [
            "11",
            "33",
            "28"
        ],
        "fecha": "07/05/2026"
    },
    {
        "nombre": "Quiniela LoteDom",
        "numeros": [
            "11",
            "55",
            "59"
        ],
        "fecha": "07/05/2026"
    },
    {
        "nombre": "El Quemaito Mayor",
        "numeros": [
            "44"
        ],
        "fecha": "07/05/2026"
    },
    {
        "nombre": "Anguila Mañana",
        "numeros": [
            "23",
            "10",
            "67"
        ],
        "fecha": "07/05/2026"
    },
    {
        "nombre": "Anguila Medio Día",
        "numeros": [
            "72",
            "53",
            "83"
        ],
        "fecha": "07/05/2026"
    },
    {
        "nombre": "Anguila Tarde",
        "numeros": [
            "70",
            "11",
            "91"
        ],
        "fecha": "07/05/2026"
    },
    {
        "nombre": "Anguila Noche",
        "numeros": [
            "31",
            "39",
            "28"
        ],
        "fecha": "07/05/2026"
    },
    {
        "nombre": "King Lottery 12:30",
        "numeros": [
            "42",
            "25",
            "27"
        ],
        "fecha": "07/05/2026"
    },
    {
        "nombre": "King Lottery 7:30",
        "numeros": [
            "25",
            "05",
            "00"
        ],
        "fecha": "07/05/2026"
    }
]